{
  "os_list": [
    {
      "name": "evcc",
      "description": "open source solar EV charging and smart heating",
      "version": "2025-10.5",
      "release_date": "2025-10-27",
      "url": "https://github.com/evcc-io/images/releases/download/v2025-10.5/armbian_evcc-2025-10.5_rpi4b.img.zip",
      "extract_size": 2730491904,
      "extract_sha256": "4198f5583838e8ac64b47c11c01be6687ccd561e7a2b2155e32594f35855610e",
      "image_download_size": 736005955,
      "image_download_sha256": "6bb8eedbf1ebf260770665ea182b82b3558d7e854c4b7b992dcca2e9e68d9082",
      "icon": "https://raw.githubusercontent.com/evcc-io/app/refs/heads/main/assets/icon-light.png",
      "website": "https://evcc.io/en/",
      "subitems_url": "",
      "devices": [
        "pi3-64bit",
        "pi4-64bit",
        "pi5-64bit"
      ]
    }
  ]
}